dsqss/__init__.py
dsqss/algorithm.py
dsqss/bosehubbard.py
dsqss/displacement.py
dsqss/dla_alg.py
dsqss/dla_pre.py
dsqss/hamiltonian.py
dsqss/lattice.py
dsqss/parameter.py
dsqss/pmwa_pre.py
dsqss/prob_kernel.py
dsqss/read_keyvalues.py
dsqss/result.py
dsqss/std_lattice.py
dsqss/std_model.py
dsqss/util.py
dsqss/wavevector.py
dsqss/xxz.py
dsqss/lattice_factory/__init__.py
dsqss/lattice_factory/honeycomb.py
dsqss/lattice_factory/hypercubic.py
dsqss/lattice_factory/kagome.py
dsqss/lattice_factory/triangular.py
dsqss-2.0.4.dist-info/METADATA
dsqss-2.0.4.dist-info/WHEEL
dsqss-2.0.4.dist-info/entry_points.txt
dsqss-2.0.4.dist-info/top_level.txt
dsqss-2.0.4.dist-info/RECORD
